LICENSE
README.md
setup.py
hcpcvlr/__init__.py
hcpcvlr.egg-info/PKG-INFO
hcpcvlr.egg-info/SOURCES.txt
hcpcvlr.egg-info/dependency_links.txt
hcpcvlr.egg-info/requires.txt
hcpcvlr.egg-info/top_level.txt
hcpcvlr/api/__init__.py
hcpcvlr/api/model_builder.py
hcpcvlr/api/pipeline/__init__.py
hcpcvlr/api/pipeline/base.py
hcpcvlr/api/pipeline/chat.py
hcpcvlr/api/pipeline/mrg.py
hcpcvlr/api/pipeline/vqa.py
hcpcvlr/data/__init__.py
hcpcvlr/data/chat_dataset.py
hcpcvlr/data/mrg_dataset.py
hcpcvlr/models/__init__.py
hcpcvlr/models/chat/__init__.py
hcpcvlr/models/chat/caco_cot.py
hcpcvlr/models/chat/cot.py
hcpcvlr/models/mrg/__init__ copy.py
hcpcvlr/models/mrg/__init__.py
hcpcvlr/models/mrg/baseline.py
hcpcvlr/models/mrg/beam_search.py
hcpcvlr/models/mrg/misc.py
hcpcvlr/models/mrg/vlci.py
hcpcvlr/models/vqa/__init__.py
hcpcvlr/modules/__init__.py
hcpcvlr/modules/backbones/__init__.py
hcpcvlr/modules/backbones/resnet.py
hcpcvlr/modules/backbones/transformer.py
hcpcvlr/modules/backbones/vision_transformer.py
hcpcvlr/modules/backbones/vit.py
hcpcvlr/modules/layers/__init__.py
hcpcvlr/modules/layers/vlci.py
hcpcvlr/modules/losses/__init__.py
hcpcvlr/modules/losses/nlg.py
hcpcvlr/modules/prompt/__init__.py
hcpcvlr/modules/prompt/caco_cot.py
hcpcvlr/modules/prompt/scienceqa_base_prompt.py
hcpcvlr/modules/tokenizers/__init__.py
hcpcvlr/modules/tokenizers/mrg_tokenizers.py
hcpcvlr/modules/utils/__init__.py
hcpcvlr/modules/utils/pos_embed.py
hcpcvlr/utils/__init__.py
hcpcvlr/utils/cfgs_loader.py
hcpcvlr/utils/device.py
hcpcvlr/utils/html.py
hcpcvlr/utils/monitor.py
hcpcvlr/utils/optimizer.py
hcpcvlr/utils/metrics/__init__.py
hcpcvlr/utils/metrics/nlg/__init__.py
hcpcvlr/utils/metrics/nlg/eval.py
hcpcvlr/utils/metrics/nlg/metrics.py
hcpcvlr/utils/metrics/nlg/bleu/__init__.py
hcpcvlr/utils/metrics/nlg/bleu/bleu.py
hcpcvlr/utils/metrics/nlg/bleu/bleu_scorer.py
hcpcvlr/utils/metrics/nlg/cider/__init__.py
hcpcvlr/utils/metrics/nlg/cider/cider.py
hcpcvlr/utils/metrics/nlg/cider/cider_scorer.py
hcpcvlr/utils/metrics/nlg/meteor/__init__.py
hcpcvlr/utils/metrics/nlg/meteor/meteor.py
hcpcvlr/utils/metrics/nlg/rouge/__init__.py
